dvim/__init__.py
dvim/__main__.py
dvim/runner.py
idzhiblavi_pydvim-0.2.12.dist-info/LICENSE
idzhiblavi_pydvim-0.2.12.dist-info/METADATA
idzhiblavi_pydvim-0.2.12.dist-info/WHEEL
idzhiblavi_pydvim-0.2.12.dist-info/entry_points.txt
idzhiblavi_pydvim-0.2.12.dist-info/top_level.txt
idzhiblavi_pydvim-0.2.12.dist-info/RECORD
